{
  "$schema": "https://mintlify.com/docs.json",
  "theme": "mint",
  "name": "Stack Events Docs",
  "colors": {
    "primary": "#2856a6",
    "light": "#3c5e99",
    "dark": "#1e2f5e"
  },
  "favicon": "/favicon.svg",
"navigation": {
  "tabs": [
    {
      "tab": "Media Essentials",
      "groups": [
        {
          "group": "Getting Started",
          "pages": [
            "media/getting-started/index",
            "media/getting-started/logging-in",
            "media/getting-started/signing-up",
            "media/getting-started/resetting-password",
            "media/getting-started/navigation-overview",
            "media/getting-started/switching-products"
          ]
        },
        {
          "group": "Events",
          "pages": [
            "media/events/dashboard-overview",
            "media/events/creating-events",
            "media/events/editing-events",
            "media/events/deleting-events",
            "media/events/calendar-navigation",
            "media/events/event-types",
            "media/events/restricting-events"
          ]
        },
        {
          "group": "Users & Signups",
          "pages": [
            "media/users/assigning-students",
            "media/users/signing-up-for-event",
            "media/users/unsigning-from-event",
            "media/users/viewing-participants",
            "media/users/filtering-event-users"
          ]
        },
        {
          "group": "Submissions",
          "pages": [
            "media/submissions/creating-submissions",
            "media/submissions/uploading-images",
            "media/submissions/pasting-texts",
            "media/submissions/linking-google-docs",
            "media/submissions/viewing-submissions",
            "media/submissions/downloading-images",
            "media/submissions/reviewing-submissions",
            "media/submissions/deleting-submissions"
          ]
        },
        {
          "group": "Search & Profiles",
          "pages": [
            "media/search/advanced-search",
            "media/search/recent-submissions",
            "media/search/search-keywords-guide",
            "media/profiles/viewing-your-profile",
            "media/profiles/viewing-other-profiles",
            "media/profiles/leaderboard-overview",
            "media/profiles/leaderboard-algorithm",
            "media/profiles/how-to-rank-up"
          ]
        }
      ]
    },
    {
      "tab": "Equipment Checkout",
      "groups": [
        {
          "group": "Setup & Basics",
          "pages": [
            "checkout/setup/setup-computer",
            "checkout/setup/view-inventory",
            "checkout/setup/view-logs"
          ]
        },
        {
          "group": "Managing Gear",
          "pages": [
            "checkout/gear/add-equipment-type",
            "checkout/gear/delete-equipment-type",
            "checkout/gear/add-item",
            "checkout/gear/edit-item",
            "checkout/gear/remove-item"
          ]
        },
        {
          "group": "Checkout Process",
          "pages": [
            "checkout/process/checkout-item",
            "checkout/process/manual-checkout",
            "checkout/process/get-barcodes",
            "checkout/process/download-barcodes",
            "checkout/process/checkin-item",
            "checkout/process/mark-missing"
          ]
        },
        {
          "group": "Tracking & History",
          "pages": [
            "checkout/tracking/student-history"
          ]
        }
      ]
    },
{
  "tab": "Admin Tools",
  "groups": [
    {
      "group": "Developer Menu",
      "pages": [
        "admin/dev-menu-overview",
        "admin/configuring-story-types",
        "admin/configuring-event-types",
        "admin/global-site-settings"
      ]
    },
    {
      "group": "Managing Submissions & Users",
      "pages": [
        "admin/managing-submissions",
        "admin/editing-user-info",
        "admin/importing-users"
      ]
    }
  ]
},
{
  "tab": "Support & Billing",
  "groups": [
    {
      "group": "Support",
      "pages": [
        "support/support-account",
        "support/contacting-support",
        "support/status-page",
        "support/faq",
        "support/glossary"
      ]
    },
    {
      "group": "Billing & Plans",
      "pages": [
        "support/plans-overview",
        "support/how-billing-works",
        "support/free-trial-info",
        "support/cancel-refund-policy"
      ]
    },
    {
      "group": "Legal",
      "pages": [
        "support/terms-of-service",
        "support/privacy-policy"
      ]
    }
  ]
}
  ],
    "global": {
      "anchors": [
      {
        "anchor": "Live Demo",
        "href": "https://demo.stack.events",
        "icon": "display"
      },
      {
        "anchor": "Support",
        "href": "https://stack.events/support",
        "icon": "envelope"
      },
      {
        "anchor": "Pricing",
        "href": "https://www.stack.events/pricing-plans",
        "icon": "dollar-sign"
      },
      {
        "anchor": "Terms",
       "href": "https://www.stack.events/terms-conditions",
        "icon": "scale-balanced"
      },
      {
        "anchor": "Privacy",
        "href": "https://www.stack.events/privacy-policy",
          "icon": "shield"
      }
    ]
    }
  },
  "logo": {
    "light": "/logo/light.png",
    "dark": "/logo/dark.png"
  },
"navbar": {
  "links": [
    {
      "label": "Support",
      "href": "https://stack.events/support"
    }
  ],
  "primary": {
    "type": "button",
    "label": "Live Demo",
    "href": "https://demo.stack.events"
  }
},
"footer": {
  "socials": {
    "instagram": "https://www.instagram.com/stack.events",
    "x": "https://x.com/stack_events",
    "youtube": "https://www.youtube.com/@stack.events"
  }
}
}